hellonbdev/__init__.py
hellonbdev/_nbdev.py
hellonbdev/core.py
hellonbdev-0.0.3.dist-info/LICENSE
hellonbdev-0.0.3.dist-info/METADATA
hellonbdev-0.0.3.dist-info/WHEEL
hellonbdev-0.0.3.dist-info/entry_points.txt
hellonbdev-0.0.3.dist-info/top_level.txt
hellonbdev-0.0.3.dist-info/RECORD
