Metadata-Version: 2.1
Name: hellonbdev
Version: 0.0.3
Summary: A tutorial project for nbdev
Home-page: https://github.com/jph00/hellonbdev
Author: Jeremy Howard
Author-email: info@fast.ai
License: Apache Software License 2.0
Keywords: fast.ai nbdev tutorial
Platform: UNKNOWN
Classifier: Development Status :: 3 - Alpha
Classifier: Intended Audience :: Developers
Classifier: License :: OSI Approved :: Apache Software License
Classifier: Natural Language :: English
Classifier: Programming Language :: Python :: 3.6
Classifier: Programming Language :: Python :: 3.7
Classifier: Programming Language :: Python :: 3.8
Requires-Python: >=3.6
Requires-Dist: fastcore
